pomarkdown/__init__.py
pomarkdown/api/__init__.py
pomarkdown/api/markdown.py
pomarkdown/core/MarkdownType.py
pomarkdown/core/__init__.py
pomarkdown/lib/__init__.py
tests/__init__.py
tests/test_markdown.py
pomarkdown-0.0.3.dist-info/LICENSE
pomarkdown-0.0.3.dist-info/METADATA
pomarkdown-0.0.3.dist-info/WHEEL
pomarkdown-0.0.3.dist-info/top_level.txt
pomarkdown-0.0.3.dist-info/RECORD
