Metadata-Version: 2.1
Name: pomarkdown
Version: 0.0.3
Summary: pip install pomarkdown
Home-page: https://www.python-office.com/
Author: CoderWanFeng
Author-email: 1957875073@qq.com
License: MIT
Project-URL: Bug Tracker, https://github.com/CoderWanFeng/pomarkdown/issues
Project-URL: Documentation, https://github.com/CoderWanFeng/pomarkdown/blob/master/README.md
Project-URL: Source Code, https://github.com/CoderWanFeng/pomarkdown
Platform: any
Requires-Python: >=3.7
License-File: LICENSE
Requires-Dist: openpyxl
Requires-Dist: pandas
Requires-Dist: pofile
